scylla_arms/__init__.py
scylla_arms/config.py
scylla_arms/configparser.py
scylla_arms/main.py
scylla_arms/persisted_dicts.py
scylla_arms-0.2.0.dist-info/entry_points.txt
scylla_arms-0.2.0.dist-info/LICENSE
scylla_arms-0.2.0.dist-info/WHEEL
scylla_arms-0.2.0.dist-info/METADATA
scylla_arms-0.2.0.dist-info/RECORD
