Metadata-Version: 2.1
Name: scylla-arms
Version: 0.2.0
Summary: Tool for running Scylla tasks and pipelines
Author: Łukasz Sójka
Requires-Python: >=3.8,<4.0
Classifier: Programming Language :: Python :: 3
Classifier: Programming Language :: Python :: 3.10
Classifier: Programming Language :: Python :: 3.8
Classifier: Programming Language :: Python :: 3.9
Requires-Dist: invoke (>=1.6.0,<2.0.0)
Requires-Dist: pydantic (>=1.8.2,<2.0.0)
